edginghockeyscraper/__init__.py
edginghockeyscraper/edginghockeyscraper.py
edginghockeyscraper/data/schedule_data.py
edginghockeyscraper/util/util.py
edginghockeyscraper-0.1.6.dist-info/licenses/LICENSE
edginghockeyscraper-0.1.6.dist-info/METADATA
edginghockeyscraper-0.1.6.dist-info/WHEEL
edginghockeyscraper-0.1.6.dist-info/top_level.txt
edginghockeyscraper-0.1.6.dist-info/RECORD
