Metadata-Version: 2.4
Name: edginghockeyscraper
Version: 0.1.6
Summary: Python Hockey Data Scraper
Author-email: Austin Egri <ategri@mac.com>
Maintainer-email: Austin Egri <ategri@mac.com>
License: MIT license
Project-URL: bugs, https://github.com/austinegri/edginghockeyscraper/issues
Project-URL: changelog, https://github.com/austinegri/edginghockeyscraper/blob/master/changelog.md
Project-URL: homepage, https://github.com/austinegri/edginghockeyscraper
License-File: LICENSE
Requires-Dist: pip>=24.3.1
Requires-Dist: wheel>=0.45.1
Requires-Dist: twine==5.1.1
Requires-Dist: setuptools>=62.6.0
Requires-Dist: requests-cache~=1.2.1
Requires-Dist: requests~=2.32.3
Provides-Extra: dev
Requires-Dist: coverage; extra == "dev"
Requires-Dist: mypy; extra == "dev"
Requires-Dist: pytest; extra == "dev"
Requires-Dist: ruff; extra == "dev"
Dynamic: license-file
